python_catalyst/__init__.py
python_catalyst/client.py
python_catalyst/enums.py
python_catalyst/stix_converter.py
python_catalyst-0.1.6.dist-info/licenses/LICENSE
tests/__init__.py
tests/conftest.py
tests/test_client.py
tests/test_integration.py
tests/test_stix_converter.py
python_catalyst-0.1.6.dist-info/METADATA
python_catalyst-0.1.6.dist-info/WHEEL
python_catalyst-0.1.6.dist-info/top_level.txt
python_catalyst-0.1.6.dist-info/RECORD
