Metadata-Version: 2.4
Name: python-catalyst
Version: 0.1.6
Summary: Python client for the PRODAFT CATALYST API
Home-page: https://github.com/prodaft/python-catalyst
Author: PRODAFT
Author-email: PRODAFT <catalyst+pypi@prodaft.com>
License: MIT License
Project-URL: Homepage, https://github.com/prodaft/python-catalyst
Project-URL: Documentation, https://github.com/prodaft/python-catalyst
Project-URL: Source, https://github.com/prodaft/python-catalyst
Keywords: prodaft,catalyst,threat intelligence,stix,opencti
Classifier: Programming Language :: Python :: 3
Classifier: Programming Language :: Python :: 3.8
Classifier: Programming Language :: Python :: 3.9
Classifier: Programming Language :: Python :: 3.10
Classifier: Programming Language :: Python :: 3.11
Classifier: License :: OSI Approved :: MIT License
Classifier: Operating System :: OS Independent
Classifier: Development Status :: 4 - Beta
Classifier: Intended Audience :: Developers
Classifier: Intended Audience :: Information Technology
Classifier: Topic :: Security
Requires-Python: >=3.8
License-File: LICENSE
Requires-Dist: requests>=2.25.0
Requires-Dist: stix2>=3.0.0
Requires-Dist: python-dateutil>=2.9.0
Requires-Dist: pycti>=6.5.8
Dynamic: author
Dynamic: home-page
Dynamic: license-file
Dynamic: requires-python
